reinfolib/__init__.py
reinfolib/api_client.py
reinfolib/api_http_client.py
reinfolib/models.py
reinfolib_api_client-0.1.4.dist-info/METADATA
reinfolib_api_client-0.1.4.dist-info/WHEEL
reinfolib_api_client-0.1.4.dist-info/RECORD
