Metadata-Version: 2.1
Name: reinfolib-api-client
Version: 0.1.4
Summary: A reinfolib(不動産情報ライブラリ) API client for Python
Author: ysm001
Author-email: ry.ysd01@gmail.com
Requires-Python: >=3.11,<4.0
Classifier: Programming Language :: Python :: 3
Classifier: Programming Language :: Python :: 3.11
Classifier: Programming Language :: Python :: 3.12
Requires-Dist: pydantic (>=2.8.2,<3.0.0)
Requires-Dist: requests (>=2.32.3,<3.0.0)
